ai_video_assistant/__init__.py
ai_video_assistant/analyzer.py
ai_video_assistant/audio_extractor.py
ai_video_assistant/core.py
ai_video_assistant/ffmpeg_utils.py
ai_video_assistant/subtitle_generator.py
ai_video_assistant/transcriber.py
ai_video_assistant/word_generator.py
ai_video_assistant-1.0.5.dist-info/licenses/LICENSE
ai_video_assistant-1.0.5.dist-info/METADATA
ai_video_assistant-1.0.5.dist-info/WHEEL
ai_video_assistant-1.0.5.dist-info/entry_points.txt
ai_video_assistant-1.0.5.dist-info/top_level.txt
ai_video_assistant-1.0.5.dist-info/RECORD
