Metadata-Version: 2.4
Name: ai-video-assistant
Version: 1.0.5
Summary: AI-powered video lecture transcription, analysis, and subtitle generation
Home-page: https://github.com/Aditya-Takawale/AI-Summary
Author: Aditya Takawale
Author-email: adityatakawale@example.com
Classifier: Development Status :: 4 - Beta
Classifier: Intended Audience :: Developers
Classifier: Intended Audience :: Education
Classifier: Topic :: Education
Classifier: Topic :: Multimedia :: Video
Classifier: License :: OSI Approved :: MIT License
Classifier: Programming Language :: Python :: 3
Classifier: Programming Language :: Python :: 3.9
Classifier: Programming Language :: Python :: 3.10
Classifier: Programming Language :: Python :: 3.11
Classifier: Programming Language :: Python :: 3.12
Classifier: Programming Language :: Python :: 3.13
Classifier: Operating System :: OS Independent
Classifier: Operating System :: Microsoft :: Windows
Classifier: Operating System :: POSIX :: Linux
Classifier: Operating System :: MacOS
Requires-Python: >=3.9
License-File: LICENSE
Requires-Dist: openai-whisper>=20231117
Requires-Dist: moviepy>=1.0.3
Requires-Dist: requests>=2.31.0
Requires-Dist: python-docx>=1.1.0
Requires-Dist: Pillow>=10.0.0
Requires-Dist: opencv-python>=4.8.0
Requires-Dist: torch>=2.0.0
Requires-Dist: torchaudio>=2.0.0
Requires-Dist: imageio-ffmpeg>=0.4.9
Provides-Extra: web
Requires-Dist: flask>=3.0.0; extra == "web"
Provides-Extra: dev
Requires-Dist: pytest>=7.0.0; extra == "dev"
Requires-Dist: black>=23.0.0; extra == "dev"
Dynamic: author
Dynamic: author-email
Dynamic: classifier
Dynamic: description
Dynamic: description-content-type
Dynamic: home-page
Dynamic: license-file
Dynamic: provides-extra
Dynamic: requires-dist
Dynamic: requires-python
Dynamic: summary
